oswin_tempest_plugin/__init__.py
oswin_tempest_plugin/config.py
oswin_tempest_plugin/exceptions.py
oswin_tempest_plugin/plugin.py
oswin_tempest_plugin/clients/__init__.py
oswin_tempest_plugin/clients/wsman.py
oswin_tempest_plugin/services/__init__.py
oswin_tempest_plugin/services/gnocchi_client.py
oswin_tempest_plugin/tests/__init__.py
oswin_tempest_plugin/tests/test_base.py
oswin_tempest_plugin/tests/_mixins/__init__.py
oswin_tempest_plugin/tests/_mixins/migrate.py
oswin_tempest_plugin/tests/_mixins/optional_feature.py
oswin_tempest_plugin/tests/_mixins/resize.py
oswin_tempest_plugin/tests/scenario/__init__.py
oswin_tempest_plugin/tests/scenario/test_cluster.py
oswin_tempest_plugin/tests/scenario/test_disks.py
oswin_tempest_plugin/tests/scenario/test_metrics_collection.py
oswin_tempest_plugin/tests/scenario/test_qos.py
oswin_tempest_plugin/tests/scenario/test_remotefx.py
oswin_tempest_plugin/tests/scenario/test_secure_boot.py
oswin_tempest_plugin/tests/scenario/test_vnuma.py
oswin_tempest_plugin-2.1.0.dist-info/AUTHORS
oswin_tempest_plugin-2.1.0.dist-info/LICENSE
oswin_tempest_plugin-2.1.0.dist-info/METADATA
oswin_tempest_plugin-2.1.0.dist-info/WHEEL
oswin_tempest_plugin-2.1.0.dist-info/entry_points.txt
oswin_tempest_plugin-2.1.0.dist-info/pbr.json
oswin_tempest_plugin-2.1.0.dist-info/top_level.txt
oswin_tempest_plugin-2.1.0.dist-info/RECORD
