Metadata-Version: 2.1
Name: oswin-tempest-plugin
Version: 2.1.0
Summary: This project contains Tempest tests to cover the os_win project, as well as a plugin to automatically load these tests into Tempest.
Home-page: https://opendev.org/openstack/oswin-tempest-plugin
Author: Cloudbase Solutions
Author-email: info@cloudbasesolutions.com
License: UNKNOWN
Platform: UNKNOWN
Classifier: Environment :: OpenStack
Classifier: Intended Audience :: Information Technology
Classifier: Intended Audience :: System Administrators
Classifier: License :: OSI Approved :: Apache Software License
Classifier: Operating System :: POSIX :: Linux
Classifier: Operating System :: Microsoft :: Windows
Classifier: Programming Language :: Python
Classifier: Programming Language :: Python :: 3
Classifier: Programming Language :: Python :: 3.8
Requires-Python: >=3.8
Requires-Dist: oslo.config (>=5.1.0)
Requires-Dist: oslo.log (>=3.36.0)
Requires-Dist: oslo.utils (>=3.33.0)
Requires-Dist: pbr (!=2.1.0,>=2.0.0)
Requires-Dist: pywinrm (>=0.2.2)
Requires-Dist: tempest (>=17.1.0)
